l10n_uy_api/__init__.py
l10n_uy_api/uruware_api/__init__.py
l10n_uy_api/uruware_api/connector/__init__.py
l10n_uy_api/uruware_api/connector/connector.py
l10n_uy_api/uruware_api/connector/req_body.py
l10n_uy_api/uruware_api/connector/ucfe_requirement.py
l10n_uy_api/uruware_api/manager/__init__.py
l10n_uy_api/uruware_api/manager/batch_manager.py
l10n_uy_api/uruware_api/manager/manager.py
l10n_uy_api/uruware_api/manager/req_body.py
l10n_uy_api/uruware_api/manager/ucfe_requirement.py
l10n_uy_api/uruware_api/test/__init__.py
l10n_uy_api/uruware_api/test/objects.py
l10n_uy_api/uruware_api/test/test_uruware.py
l10n_uy_api-2.0.17.dist-info/METADATA
l10n_uy_api-2.0.17.dist-info/WHEEL
l10n_uy_api-2.0.17.dist-info/top_level.txt
l10n_uy_api-2.0.17.dist-info/RECORD
