Metadata-Version: 2.4
Name: l10n_uy_api
Version: 2.0.17
Summary: Libreria para localizacion Uruguaya
Home-page: 
Author: BLUEORANGE GROUP
Author-email: daniel@blueorange.com.ar
Keywords: Libreria para localizacion Uruguaya
Classifier: Development Status :: 4 - Beta
Classifier: Intended Audience :: Developers
Classifier: Topic :: Software Development
Classifier: Programming Language :: Python :: 2.7
Classifier: Programming Language :: Python :: 3
Classifier: Programming Language :: Python :: 3.4
Classifier: Programming Language :: Python :: 3.5
Classifier: Programming Language :: Python :: 3.6
Requires-Dist: zeep
Requires-Dist: python-dateutil
Requires-Dist: pytz
Requires-Dist: unidecode==1.2.0
Requires-Dist: BeautifulSoup4==4.9.3
Dynamic: author
Dynamic: author-email
Dynamic: classifier
Dynamic: description
Dynamic: keywords
Dynamic: requires-dist
Dynamic: summary
